mychtool
