Metadata-Version: 1.0
Name: mychtool
Version: 1.0.2
Summary: My ClickHouse Tool
Home-page: UNKNOWN
Author: Zhou Fang
Author-email: thomas.zhouf@hotmail.com
License: UNKNOWN
Platform: UNKNOWN
